pynpdc/__init__.py
pynpdc/auth_client.py
pynpdc/data_client.py
pynpdc/exception.py
pynpdc/models.py
pynpdc/py.typed
pynpdc/utils.py
pynpdc-0.30.0.dist-info/METADATA
pynpdc-0.30.0.dist-info/WHEEL
pynpdc-0.30.0.dist-info/top_level.txt
pynpdc-0.30.0.dist-info/RECORD
