Metadata-Version: 2.4
Name: pynpdc
Version: 0.30.0
Summary: Python lib to interact with the NPDC stack of the Norwegian Polar Institute
Author-email: Olaf Schneider <olaf.schneider@npolar.no>
License-Expression: MIT
Project-URL: Changelog, https://gitlab.npolar.no/npdc/core/pynpdc/-/blob/main/CHANGELOG.md
Project-URL: Homepage, https://gitlab.npolar.no/npdc/core/pynpdc
Project-URL: Source, https://gitlab.npolar.no/npdc/core/pynpdc
Classifier: Development Status :: 4 - Beta
Classifier: Intended Audience :: Developers
Classifier: Intended Audience :: Science/Research
Classifier: Programming Language :: Python :: 3
Classifier: Programming Language :: Python :: 3.10
Classifier: Programming Language :: Python :: 3.11
Classifier: Programming Language :: Python :: 3.12
Classifier: Programming Language :: Python :: 3.13
Classifier: Programming Language :: Python :: 3.14
Classifier: Typing :: Typed
Requires-Python: >=3.10
Requires-Dist: requests
Requires-Dist: requests-toolbelt
Requires-Dist: typing-extensions
Requires-Dist: werkzeug
